tensorflow_addons_theo-0.23.0.dev0.data/purelib/tensorflow_addons/__init__.py
tensorflow_addons_theo-0.23.0.dev0.data/purelib/tensorflow_addons/conftest.py
tensorflow_addons_theo-0.23.0.dev0.data/purelib/tensorflow_addons/options.py
tensorflow_addons_theo-0.23.0.dev0.data/purelib/tensorflow_addons/register.py
tensorflow_addons_theo-0.23.0.dev0.data/purelib/tensorflow_addons/version.py
tensorflow_addons_theo-0.23.0.dev0.data/purelib/tensorflow_addons/activations/__init__.py
tensorflow_addons_theo-0.23.0.dev0.data/purelib/tensorflow_addons/activations/gelu.py
tensorflow_addons_theo-0.23.0.dev0.data/purelib/tensorflow_addons/activations/hardshrink.py
tensorflow_addons_theo-0.23.0.dev0.data/purelib/tensorflow_addons/activations/lisht.py
tensorflow_addons_theo-0.23.0.dev0.data/purelib/tensorflow_addons/activations/mish.py
tensorflow_addons_theo-0.23.0.dev0.data/purelib/tensorflow_addons/activations/rrelu.py
tensorflow_addons_theo-0.23.0.dev0.data/purelib/tensorflow_addons/activations/snake.py
tensorflow_addons_theo-0.23.0.dev0.data/purelib/tensorflow_addons/activations/softshrink.py
tensorflow_addons_theo-0.23.0.dev0.data/purelib/tensorflow_addons/activations/sparsemax.py
tensorflow_addons_theo-0.23.0.dev0.data/purelib/tensorflow_addons/activations/tanhshrink.py
tensorflow_addons_theo-0.23.0.dev0.data/purelib/tensorflow_addons/activations/tests/__init__.py
tensorflow_addons_theo-0.23.0.dev0.data/purelib/tensorflow_addons/activations/tests/activations_test.py
tensorflow_addons_theo-0.23.0.dev0.data/purelib/tensorflow_addons/activations/tests/gelu_test.py
tensorflow_addons_theo-0.23.0.dev0.data/purelib/tensorflow_addons/activations/tests/hardshrink_test.py
tensorflow_addons_theo-0.23.0.dev0.data/purelib/tensorflow_addons/activations/tests/lisht_test.py
tensorflow_addons_theo-0.23.0.dev0.data/purelib/tensorflow_addons/activations/tests/mish_test.py
tensorflow_addons_theo-0.23.0.dev0.data/purelib/tensorflow_addons/activations/tests/rrelu_test.py
tensorflow_addons_theo-0.23.0.dev0.dist-info/LICENSE
tensorflow_addons_theo-0.23.0.dev0.dist-info/METADATA
tensorflow_addons_theo-0.23.0.dev0.dist-info/WHEEL
tensorflow_addons_theo-0.23.0.dev0.dist-info/top_level.txt
tensorflow_addons_theo-0.23.0.dev0.dist-info/RECORD
